LICENSE
MANIFEST.in
README.md
setup.py
englishcards/__init__.py
englishcards/__main__.py
englishcards/_main.py
englishcards.egg-info/PKG-INFO
englishcards.egg-info/SOURCES.txt
englishcards.egg-info/dependency_links.txt
englishcards.egg-info/entry_points.txt
englishcards.egg-info/top_level.txt