Metadata-Version: 2.1
Name: englishcards
Version: 0.1a1
Summary: Flash cards app for learning English
Home-page: https://github.com/kosarev/englishcards/
Author: Ivan Kosarev
Author-email: ivan@kosarev.info
License: MIT
Platform: UNKNOWN
Classifier: Development Status :: 2 - Pre-Alpha
Classifier: Environment :: Console
Classifier: Environment :: X11 Applications :: GTK
Classifier: Intended Audience :: Education
Classifier: Intended Audience :: End Users/Desktop
Classifier: License :: OSI Approved :: MIT License
Classifier: Operating System :: OS Independent
Classifier: Natural Language :: English
Classifier: Programming Language :: Python
Classifier: Programming Language :: Python :: 3
Classifier: Topic :: Education
Classifier: Topic :: Education :: Testing
